jupyterlab4_sysmlv2/__init__.py
jupyterlab4_sysmlv2/_version.py
jupyterlab4_sysmlv2/labextension/package.json
jupyterlab4_sysmlv2/labextension/static/358.43b28f8341591d3e235a.js
jupyterlab4_sysmlv2/labextension/static/358.43b28f8341591d3e235a.js.LICENSE.txt
jupyterlab4_sysmlv2/labextension/static/728.dcbff4f9988630210468.js
jupyterlab4_sysmlv2/labextension/static/remoteEntry.b0c0a1a4cede5de4ce67.js
jupyterlab4_sysmlv2/labextension/static/style.js
jupyterlab4_sysmlv2/labextension/static/third-party-licenses.json
jupyterlab4_sysmlv2-0.1.0.data/data/share/jupyter/labextensions/jupyterlab4_sysmlv2/package.json
jupyterlab4_sysmlv2-0.1.0.data/data/share/jupyter/labextensions/jupyterlab4_sysmlv2/static/358.43b28f8341591d3e235a.js
jupyterlab4_sysmlv2-0.1.0.data/data/share/jupyter/labextensions/jupyterlab4_sysmlv2/static/358.43b28f8341591d3e235a.js.LICENSE.txt
jupyterlab4_sysmlv2-0.1.0.data/data/share/jupyter/labextensions/jupyterlab4_sysmlv2/static/728.dcbff4f9988630210468.js
jupyterlab4_sysmlv2-0.1.0.data/data/share/jupyter/labextensions/jupyterlab4_sysmlv2/static/remoteEntry.b0c0a1a4cede5de4ce67.js
jupyterlab4_sysmlv2-0.1.0.data/data/share/jupyter/labextensions/jupyterlab4_sysmlv2/static/style.js
jupyterlab4_sysmlv2-0.1.0.data/data/share/jupyter/labextensions/jupyterlab4_sysmlv2/static/third-party-licenses.json
jupyterlab4_sysmlv2-0.1.0.data/data/share/jupyter/labextensions/jupyterlab4_sysmlv2/install.json
jupyterlab4_sysmlv2-0.1.0.dist-info/METADATA
jupyterlab4_sysmlv2-0.1.0.dist-info/WHEEL
jupyterlab4_sysmlv2-0.1.0.dist-info/licenses/LICENSE
jupyterlab4_sysmlv2-0.1.0.dist-info/RECORD
