Metadata-Version: 2.4
Name: jupyterlab4_sysmlv2
Version: 0.1.0
Summary: Syntax highlighting for SysMLv2.
Project-URL: Homepage, https://github.com/FreeAndFair/JupyterLab-SysMLv2-Plugin
Project-URL: Bug Tracker, https://github.com/FreeAndFair/JupyterLab-SysMLv2-Plugin/issues
Project-URL: Repository, https://github.com/FreeAndFair/JupyterLab-SysMLv2-Plugin.git
Author-email: "Daniel M. Zimmerma" <dmz@freeandfair.us>
License:                    GNU LESSER GENERAL PUBLIC LICENSE
License-File: LICENSE
Keywords: jupyter,jupyterlab,jupyterlab-extension
Classifier: Framework :: Jupyter
Classifier: Framework :: Jupyter :: JupyterLab
Classifier: Framework :: Jupyter :: JupyterLab :: 4
Classifier: Framework :: Jupyter :: JupyterLab :: Extensions
Classifier: Framework :: Jupyter :: JupyterLab :: Extensions :: Prebuilt
Classifier: License :: OSI Approved :: BSD License
Classifier: Programming Language :: Python
Classifier: Programming Language :: Python :: 3
Classifier: Programming Language :: Python :: 3.8
Classifier: Programming Language :: Python :: 3.9
Classifier: Programming Language :: Python :: 3.10
Classifier: Programming Language :: Python :: 3.11
Classifier: Programming Language :: Python :: 3.12
Requires-Python: >=3.8
